flaask/__init__.py
flaask-0.0.4.dist-info/METADATA
flaask-0.0.4.dist-info/WHEEL
flaask-0.0.4.dist-info/top_level.txt
flaask-0.0.4.dist-info/RECORD
