Metadata-Version: 2.4
Name: flaask
Version: 0.0.4
Summary: ⚠️ Typo protection: You probably meant 'flask'. This is a defensive registration against typosquatting.
Author: Security Researcher
License: MIT
Project-URL: Correct Package, https://pypi.org/project/requests/
Project-URL: Why This Exists, https://en.wikipedia.org/wiki/Typosquatting
Keywords: typosquatting,security,requests,typo,protection
Classifier: Development Status :: 1 - Planning
Classifier: Intended Audience :: Developers
Classifier: License :: OSI Approved :: MIT License
Classifier: Programming Language :: Python :: 3
Classifier: Topic :: Security
Requires-Python: >=3.6
Dynamic: requires-python
